dynamic_function_loader/__init__.py
dynamic_function_loader-0.0.3.dist-info/LICENSE
dynamic_function_loader-0.0.3.dist-info/METADATA
dynamic_function_loader-0.0.3.dist-info/WHEEL
dynamic_function_loader-0.0.3.dist-info/top_level.txt
dynamic_function_loader-0.0.3.dist-info/RECORD
