Metadata-Version: 2.1
Name: dynamic-function-loader
Version: 0.0.3
Summary: Dynamically loads a function from code represented as a string.
Home-page: https://github.com/QuiNovas/dynamic-function-loader
Author: Joseph Wortmann
Author-email: jwortmann@quinovas.com
License: Apache 2.0
Platform: UNKNOWN
Classifier: Development Status :: 4 - Beta
Classifier: Intended Audience :: Developers
Classifier: License :: OSI Approved :: Apache Software License
Classifier: Programming Language :: Python :: 3.8
